{
    "maximum_G11": {
        "value": 1.348620884738879,
        "frames": [
            "frame399"
        ]
    },
    "maximum_G12": {
        "value": 1.6427775422662574,
        "frames": [
            "frame399"
        ]
    },
    "maximum_G13": {
        "value": -0.27734005028211284,
        "frames": [
            "frame563"
        ]
    },
    "maximum_X_story_drift": {
        "value": -0.9493175709615977,
        "node": "nodes839"
    },
    "maximum_Y_story_drift": {
        "value": -0.6741711653640627,
        "node": "nodes741"
    },
    "maximum_X_abs_story_drift": {
        "value": -0.9094871497134978,
        "node": "nodes791"
    },
    "maximum_Y_abs_story_drift": {
        "value": -0.7070464546488473,
        "node": "nodes268"
    },
    "total_weight": {
        "value": 383.53838976000145
    }
}